Metadata-Version: 2.1
Name: example_package_sundebin
Version: 0.0.2
Summary: A small example package
Author-email: sundebin68 <sundebin68@gmail.com>
Project-URL: Homepage, https://github.com/pypa/sampleproject
Project-URL: Issues, https://github.com/pypa/sampleproject/issues
Classifier: Programming Language :: Python :: 3
Classifier: License :: OSI Approved :: MIT License
Classifier: Operating System :: OS Independent
Requires-Python: >=3.8
License-File: LICENSE
